prime_bits/__init__.py
prime_bits/prime_bits.py
prime_bits/utils.py
prime_bits-1.0.6.dist-info/licenses/LICENSE
prime_bits-1.0.6.dist-info/METADATA
prime_bits-1.0.6.dist-info/WHEEL
prime_bits-1.0.6.dist-info/top_level.txt
prime_bits-1.0.6.dist-info/RECORD
