Metadata-Version: 2.4
Name: prime_bits
Version: 1.0.6
Summary: A package to get prime numbers from bits.
Home-page: https://github.com/Zikithezikit/prime_bits
Author: Zikithezikit
Author-email: zikithezikit@example.com
License: MIT
Keywords: prime number bits large
Classifier: Programming Language :: Python :: 3
Classifier: License :: OSI Approved :: MIT License
Classifier: Operating System :: OS Independent
Requires-Python: >=3.6
License-File: LICENSE
Dynamic: author
Dynamic: author-email
Dynamic: classifier
Dynamic: description
Dynamic: description-content-type
Dynamic: home-page
Dynamic: keywords
Dynamic: license
Dynamic: license-file
Dynamic: requires-python
Dynamic: summary
